[
    {
        "review_date": "2022-01-28",
        "count": 0,
        "avg": 0
    },
    {
        "review_date": "2022-02-28",
        "count": 0,
        "avg": 0
    },
    {
        "review_date": "2022-03-28",
        "count": 0,
        "avg": 0
    },
    {
        "review_date": "2022-04-28",
        "count": 0,
        "avg": 0
    },
    {
        "review_date": "2022-05-28",
        "count": 0,
        "avg": 0
    },
    {
        "review_date": "2022-06-28",
        "count": 0,
        "avg": 0
    },
    {
        "review_date": "2022-07-28",
        "count": 0,
        "avg": 0
    },
    {
        "review_date": "2022-08-28",
        "count": 0,
        "avg": 0
    },
    {
        "review_date": "2022-09-28",
        "count": 0,
        "avg": 0
    },
    {
        "review_date": "2022-10-28",
        "count": 0,
        "avg": 0
    },
    {
        "review_date": "2022-11-28",
        "count": 0,
        "avg": 0
    },
    {
        "review_date": "2022-12-28",
        "count": 0,
        "avg": 0
    }
]